whatsapp_api/__init__.py
whatsapp_api/base_client.py
whatsapp_api/media/__init__.py
whatsapp_api/media/media_client.py
whatsapp_api/message/__init__.py
whatsapp_api/message/messaging.py
whatsapp_api/message/validation.py
whatsapp_api_connect-0.0.7.dist-info/licenses/LICENSE
whatsapp_api_connect-0.0.7.dist-info/METADATA
whatsapp_api_connect-0.0.7.dist-info/WHEEL
whatsapp_api_connect-0.0.7.dist-info/top_level.txt
whatsapp_api_connect-0.0.7.dist-info/RECORD
