Metadata-Version: 2.4
Name: whatsapp-api-connect
Version: 0.0.7
Summary: Python wrapper for the Meta WhatsApp API
Author-email: Md Mahiuddin <dev.mahiuddin@gmail.com>
License: MIT
Keywords: whatsapp,api,connect
Classifier: Programming Language :: Python :: 3
Classifier: License :: OSI Approved :: MIT License
Classifier: Operating System :: OS Independent
License-File: LICENSE
Requires-Dist: requests>=2.32.3
Dynamic: license-file
